main.py
auto_git_msg-0.1.1.dist-info/licenses/LICENSE
auto_git_msg-0.1.1.dist-info/METADATA
auto_git_msg-0.1.1.dist-info/WHEEL
auto_git_msg-0.1.1.dist-info/entry_points.txt
auto_git_msg-0.1.1.dist-info/top_level.txt
auto_git_msg-0.1.1.dist-info/RECORD
