Metadata-Version: 2.4
Name: auto-git-msg
Version: 0.1.1
Summary: Add your description here
Requires-Python: >=3.10
License-File: LICENSE
Requires-Dist: autogemini>=0.1.3.post3
Requires-Dist: colorama>=0.4.6
Requires-Dist: html2text>=2025.4.15
Dynamic: license-file
